rongcloud/__init__.py
rongcloud/chatroom.py
rongcloud/conversation.py
rongcloud/group.py
rongcloud/message.py
rongcloud/module.py
rongcloud/push.py
rongcloud/rongcloud.py
rongcloud/sensitive.py
rongcloud/user.py
rc_server_sdk-3.2.0.dist-info/LICENSE
rc_server_sdk-3.2.0.dist-info/METADATA
rc_server_sdk-3.2.0.dist-info/WHEEL
rc_server_sdk-3.2.0.dist-info/top_level.txt
rc_server_sdk-3.2.0.dist-info/RECORD
