Metadata-Version: 2.1
Name: rc-server-sdk
Version: 3.2.0
Summary: rongcloud python server sdk
Home-page: https://github.com/rongcloud/server-sdk-python
Author: zhanglei1
Author-email: zhanglei1@rongcloud.cn
License: UNKNOWN
Platform: UNKNOWN
Classifier: Programming Language :: Python :: 3
Classifier: License :: OSI Approved :: MIT License
Classifier: Operating System :: OS Independent
